gemmap/__init__.py
gemmap/_bipartite.py
gemmap/_monopartite.py
gemmap/_netcore.py
gemmap/_pimping.py
gemmap/annotation.gemmap_data
gemmap/mapping.gemmap_data
gemmap-0.1.3.dist-info/LICENSE
gemmap-0.1.3.dist-info/METADATA
gemmap-0.1.3.dist-info/WHEEL
gemmap-0.1.3.dist-info/RECORD
