Metadata-Version: 2.1
Name: gemmap
Version: 0.1.3
Summary: 
License: GNU General Public License v3.0
Author: Gioele Lazzari
Requires-Python: >=3.9,<3.10
Classifier: License :: Other/Proprietary License
Classifier: Programming Language :: Python :: 3
Classifier: Programming Language :: Python :: 3.9
Requires-Dist: biopython (>=1.79)
Requires-Dist: cobra (>=0.26)
Requires-Dist: ipycytoscape (>=1.3.3)
Requires-Dist: openpyxl (>=3.1.0)
Requires-Dist: pandas (>=1.5)
Requires-Dist: pygraphviz (>=1.10)
Requires-Dist: pyvis (>=0.3)
Requires-Dist: requests (>=2.28)
